{
  "taskRoute": {
    "waypoints": [
      {
        "lat": 43.80345731,
        "lng": 16.48830266
      },
      {
        "lat": 43.83719201,
        "lng": 16.47702492
      },
      {
        "lat": 43.8246942,
        "lng": 16.52817358
      },
      {
        "lat": 43.79828094,
        "lng": 16.50256955
      },
      {
        "lat": 43.78840019,
        "lng": 16.5891443
      },
      {
        "lat": 43.75968648,
        "lng": 16.61726811
      }
    ],
    "flipSum": [
      "22.750177 km",
      "18.893716 km",
      "14.551616 km",
      "10.965995 km",
      "3.912153 km"
    ],
    "distance": "22.750177 km",
    "legsSum": [
      "3.856461 km",
      "8.198561 km",
      "11.784182 km",
      "18.838025 km",
      "22.750177 km"
    ],
    "legs": [
      "3.856461 km",
      "4.342101 km",
      "3.585621 km",
      "7.053843 km",
      "3.912153 km"
    ]
  },
  "startRoute": {
    "waypoints": [
      {
        "lat": 43.80288173,
        "lng": 16.48599279
      },
      {
        "lat": 43.83270357,
        "lng": 16.46758928
      }
    ],
    "flipSum": [
      "3.629213 km"
    ],
    "distance": "3.629213 km",
    "legsSum": [
      "3.629213 km"
    ],
    "legs": [
      "3.629213 km"
    ]
  },
  "taskRouteSpeedSubset": {
    "waypoints": [
      {
        "lat": 43.80345731,
        "lng": 16.48830266
      },
      {
        "lat": 43.83719201,
        "lng": 16.47702492
      },
      {
        "lat": 43.8246942,
        "lng": 16.52817358
      },
      {
        "lat": 43.79828094,
        "lng": 16.50256955
      },
      {
        "lat": 43.78840019,
        "lng": 16.5891443
      },
      {
        "lat": 43.75968648,
        "lng": 16.61726811
      }
    ],
    "flipSum": [
      "22.750177 km",
      "18.893716 km",
      "14.551616 km",
      "10.965995 km",
      "3.912153 km"
    ],
    "distance": "22.750177 km",
    "legsSum": [
      "3.856461 km",
      "8.198561 km",
      "11.784182 km",
      "18.838025 km",
      "22.750177 km"
    ],
    "legs": [
      "3.856461 km",
      "4.342101 km",
      "3.585621 km",
      "7.053843 km",
      "3.912153 km"
    ]
  },
  "speedRoute": {
    "waypoints": [
      {
        "lat": 43.80345731,
        "lng": 16.48830266
      },
      {
        "lat": 43.83719201,
        "lng": 16.47702492
      },
      {
        "lat": 43.8246942,
        "lng": 16.52817358
      },
      {
        "lat": 43.79828094,
        "lng": 16.50256955
      },
      {
        "lat": 43.78840019,
        "lng": 16.5891443
      },
      {
        "lat": 43.75968648,
        "lng": 16.61726811
      }
    ],
    "flipSum": [
      "22.750177 km",
      "18.893716 km",
      "14.551616 km",
      "10.965995 km",
      "3.912153 km"
    ],
    "distance": "22.750177 km",
    "legsSum": [
      "3.856461 km",
      "8.198561 km",
      "11.784182 km",
      "18.838025 km",
      "22.750177 km"
    ],
    "legs": [
      "3.856461 km",
      "4.342101 km",
      "3.585621 km",
      "7.053843 km",
      "3.912153 km"
    ]
  },
  "stopRoute": {
    "waypoints": [
      {
        "lat": 43.80345731,
        "lng": 16.48830266
      },
      {
        "lat": 43.83719201,
        "lng": 16.47702492
      },
      {
        "lat": 43.8246942,
        "lng": 16.52817358
      },
      {
        "lat": 43.79828094,
        "lng": 16.50256955
      },
      {
        "lat": 43.78840019,
        "lng": 16.5891443
      },
      {
        "lat": 43.75968648,
        "lng": 16.61726811
      }
    ],
    "flipSum": [
      "22.750177 km",
      "18.893716 km",
      "14.551616 km",
      "10.965995 km",
      "3.912153 km"
    ],
    "distance": "22.750177 km",
    "legsSum": [
      "3.856461 km",
      "8.198561 km",
      "11.784182 km",
      "18.838025 km",
      "22.750177 km"
    ],
    "legs": [
      "3.856461 km",
      "4.342101 km",
      "3.585621 km",
      "7.053843 km",
      "3.912153 km"
    ]
  }
}
